torchmo/__init__.py
torchmo/conv.py
torchmo/observer.py
torchmo-1.0.8.dist-info/METADATA
torchmo-1.0.8.dist-info/WHEEL
torchmo-1.0.8.dist-info/RECORD
