Metadata-Version: 2.1
Name: torchmo
Version: 1.0.8
Summary: A torch observer that wraps around wanted pytorch modules
Home-page: https://github.com/AlanBlanchet/torch-module-observer.git
Author: Alan Blanchet
Author-email: alan@alan-blanchet.fr
Requires-Python: >=3.9
Classifier: Programming Language :: Python :: 3
Classifier: Programming Language :: Python :: 3.9
Classifier: Programming Language :: Python :: 3.10
Classifier: Programming Language :: Python :: 3.11
Requires-Dist: torch (>=1.3.0,!=2.0.1)
Requires-Dist: tqdm (==4.*)
Project-URL: Repository, https://github.com/AlanBlanchet/torch-module-observer.git
